Sampler.py
__init__.py
SelectSampler-0.0.1.dist-info/LICENSE
SelectSampler-0.0.1.dist-info/METADATA
SelectSampler-0.0.1.dist-info/WHEEL
SelectSampler-0.0.1.dist-info/top_level.txt
SelectSampler-0.0.1.dist-info/RECORD
