Metadata-Version: 2.1
Name: SelectSampler
Version: 0.0.1
Summary: This package allows you to fetch the dataset samples from the holoviews scatterplot as a dataframe.
Author-email: Tohya Tanemura <tohya.tanemura@kiconiaworks.com>
Classifier: Programming Language :: Python :: 3
Classifier: License :: OSI Approved :: MIT License
Classifier: Operating System :: OS Independent
Requires-Python: >=3.8
License-File: LICENSE
